nomnomdata/auth/__init__.py
nomnomdata/auth/auth.py
nomnomdata/auth/cli.py
nomnomdata/auth/util.py
nomnomdata/auth/vars.py
nomnomdata_auth-3.0.1.dist-info/COPYING
nomnomdata_auth-3.0.1.dist-info/COPYING.LESSER
nomnomdata_auth-3.0.1.dist-info/LICENSE
nomnomdata_auth-3.0.1.dist-info/METADATA
nomnomdata_auth-3.0.1.dist-info/WHEEL
nomnomdata_auth-3.0.1.dist-info/entry_points.txt
nomnomdata_auth-3.0.1.dist-info/RECORD
