Metadata-Version: 2.1
Name: nomnomdata-auth
Version: 3.0.1
Summary: Handle authorization to Nom Nom Data services
Home-page: https://gitlab.com/nomnomdata/tools/nomnomdata-auth
License: LGPL-3.0-only
Author: Nom Nom Data Inc
Author-email: info@nomnomdata.com
Requires-Python: >=3.9,<4.0
Classifier: License :: OSI Approved :: GNU Lesser General Public License v3 (LGPLv3)
Classifier: Programming Language :: Python :: 3
Classifier: Programming Language :: Python :: 3.9
Classifier: Programming Language :: Python :: 3.10
Classifier: Programming Language :: Python :: 3.11
Classifier: Programming Language :: Python :: 3.12
Classifier: Programming Language :: Python :: 3.13
Requires-Dist: dunamai (>=1.23.0,<2.0.0)
Requires-Dist: nomnomdata-cli (>=2.0.1,<3.0.0)
Requires-Dist: pycognito (>=2024.5.1,<2025.0.0)
Requires-Dist: requests (>=2.32.3,<3.0.0)
Requires-Dist: setuptools (>=75.6.0,<76.0.0)
Project-URL: Repository, https://gitlab.com/nomnomdata/tools/nomnomdata-auth
